context_verbose/__init__.py
context_verbose/color.py
context_verbose/decorator.py
context_verbose/memory.py
context_verbose/printer.py
context_verbose/singleton.py
context_verbose/thread_safe.py
context_verbose/tree.py
context_verbose-2.2.2.dist-info/licenses/LICENSE
context_verbose-2.2.2.dist-info/METADATA
context_verbose-2.2.2.dist-info/WHEEL
context_verbose-2.2.2.dist-info/top_level.txt
context_verbose-2.2.2.dist-info/RECORD
