Metadata-Version: 2.4
Name: context-verbose
Version: 2.2.2
Summary: Tool to simply display information about the state of the code during execution.
Author-email: "Robin RICHARD (robinechuca)" <serveurpython.oz@gmail.com>
Maintainer-email: "Robin RICHARD (robinechuca)" <serveurpython.oz@gmail.com>
License:                     GNU AFFERO GENERAL PUBLIC LICENSE
Project-URL: Repository, https://framagit.org/robinechuca/context-verbose
Keywords: block,context,context-printer,debug,display,print,printer,verbose
Classifier: Development Status :: 6 - Mature
Classifier: Environment :: Console
Classifier: Intended Audience :: Customer Service
Classifier: Intended Audience :: Developers
Classifier: Natural Language :: English
Classifier: Operating System :: OS Independent
Classifier: Programming Language :: Python :: 3
Classifier: Topic :: Education :: Testing
Classifier: Topic :: Printing
Classifier: Topic :: Scientific/Engineering :: Visualization
Classifier: Topic :: System :: Logging
Classifier: Topic :: Utilities
Requires-Python: >=3.10
License-File: LICENSE
Requires-Dist: colorama
Requires-Dist: networkx
Dynamic: license-file
